sag_py_logging_logstash/__init__.py
sag_py_logging_logstash/cache.py
sag_py_logging_logstash/constants.py
sag_py_logging_logstash/formatter.py
sag_py_logging_logstash/handler.py
sag_py_logging_logstash/memory_cache.py
sag_py_logging_logstash/safe_logger.py
sag_py_logging_logstash/transport.py
sag_py_logging_logstash/utils.py
sag_py_logging_logstash/worker.py
sag_py_logging_logstash-3.0.3.dist-info/licenses/LICENSE.txt
sag_py_logging_logstash-3.0.3.dist-info/METADATA
sag_py_logging_logstash-3.0.3.dist-info/WHEEL
sag_py_logging_logstash-3.0.3.dist-info/top_level.txt
sag_py_logging_logstash-3.0.3.dist-info/RECORD
