Metadata-Version: 2.4
Name: sag-py-logging-logstash
Version: 3.0.3
Summary: Python logging logstash handler
Home-page: https://github.com/SamhammerAG/sag_py_logging_logstash
Author: Samhammer AG
Author-email: support@samhammer.de
License: MIT
Project-URL: Documentation, https://github.com/SamhammerAG/sag_py_logging_logstash
Project-URL: Bug Reports, https://github.com/SamhammerAG/sag_py_logging_logstash/issues
Project-URL: Source, https://github.com/SamhammerAG/sag_py_logging_logstash
Keywords: logging,logstash
Classifier: Programming Language :: Python :: 3
Classifier: License :: OSI Approved :: MIT License
Classifier: Operating System :: OS Independent
Classifier: Topic :: Software Development :: Libraries :: Python Modules
Classifier: Topic :: Software Development :: Libraries
Classifier: Topic :: Software Development
Classifier: Topic :: System :: Logging
Requires-Python: >=3.12
License-File: LICENSE.txt
Requires-Dist: limits<6.0.0,>=5.2.0
Requires-Dist: requests>=2.32.2
Provides-Extra: dev
Requires-Dist: build>=1.2.2.post1; extra == "dev"
Requires-Dist: coverage-lcov; extra == "dev"
Requires-Dist: flake8; extra == "dev"
Requires-Dist: mock; extra == "dev"
Requires-Dist: mypy; extra == "dev"
Requires-Dist: pytest; extra == "dev"
Requires-Dist: pytest-asyncio; extra == "dev"
Requires-Dist: pytest-cov; extra == "dev"
Requires-Dist: toml; extra == "dev"
Requires-Dist: types-mock; extra == "dev"
Requires-Dist: zipp>=3.21.0; extra == "dev"
Dynamic: author
Dynamic: author-email
Dynamic: classifier
Dynamic: description
Dynamic: description-content-type
Dynamic: home-page
Dynamic: keywords
Dynamic: license
Dynamic: license-file
Dynamic: project-url
Dynamic: provides-extra
Dynamic: requires-dist
Dynamic: requires-python
Dynamic: summary
